tenark/__init__.py
tenark/arranger.py
tenark/cataloguer/__init__.py
tenark/cataloguer/cataloguer.py
tenark/cataloguer/json_cataloguer.py
tenark/cataloguer/memory_cataloguer.py
tenark/cataloguer/schema_cataloguer.py
tenark/common/__init__.py
tenark/common/exceptions.py
tenark/common/query_parser.py
tenark/common/types.py
tenark/identifier/__init__.py
tenark/identifier/identifier.py
tenark/identifier/uuid_identifier.py
tenark/models/__init__.py
tenark/models/tenant.py
tenark/provider.py
tenark/provisioner/__init__.py
tenark/provisioner/directory_provisioner.py
tenark/provisioner/memory_provisioner.py
tenark/provisioner/provisioner.py
tenark/provisioner/schema_provisioner.py
tenark/resolver.py
tenark-0.8.4.dist-info/LICENSE
tenark-0.8.4.dist-info/WHEEL
tenark-0.8.4.dist-info/METADATA
tenark-0.8.4.dist-info/RECORD
