Metadata-Version: 2.1
Name: tenark
Version: 0.8.4
Summary: Multitenancy Management Library
License: MIT
Author: Knowark
Requires-Python: >=3.8,<4.0
Classifier: License :: OSI Approved :: MIT License
Classifier: Programming Language :: Python :: 3
Classifier: Programming Language :: Python :: 3.8
